ggai/__init__.py
ggai/main.py
ggai-0.4.25.dist-info/METADATA
ggai-0.4.25.dist-info/WHEEL
ggai-0.4.25.dist-info/entry_points.txt
ggai-0.4.25.dist-info/licenses/LICENSE
ggai-0.4.25.dist-info/RECORD
