Metadata-Version: 2.4
Name: ggai
Version: 0.4.25
Summary: Helper for GeoGuessr training using OpenAI
Project-URL: Homepage, https://github.com/rioriost/homebrew-ggai
Project-URL: Issues, https://github.com/rioriost/homebrew-ggai/issues
Author-email: Rio Fujita <rifujita@microsoft.com>
License: MIT License
License-File: LICENSE
Requires-Python: >=3.10
Requires-Dist: openai>=2.15.0
Requires-Dist: pillow>=12.1.0
Requires-Dist: pyobjc>=12.1
